wenbi/__init__.py
wenbi/batch.py
wenbi/batch.py.backup
wenbi/cli.py
wenbi/cli.py.current
wenbi/download.py
wenbi/enhanced_combination.py
wenbi/gui.py
wenbi/main.py
wenbi/main.py.backup
wenbi/main.py.backup.pre-fix
wenbi/model.py
wenbi/model.py.backup
wenbi/model.py.backup.pre-fix
wenbi/mutilang.py
wenbi/ppt_integration.py
wenbi/utils.py
wenbi/utils.py.backup
wenbi/video_slides.py
wenbi/llm/gemini.py
wenbi/llm/ollama.py
wenbi-0.140.81.dist-info/METADATA
wenbi-0.140.81.dist-info/WHEEL
wenbi-0.140.81.dist-info/entry_points.txt
wenbi-0.140.81.dist-info/RECORD
