Metadata-Version: 2.3
Name: wenbi
Version: 0.140.81
Summary: A simple tool to make the video, audio, subtitle and video-url (especially youtube) content into a written markdown files with the ability to rewritten the oral expression into written ones, or translating the content into a target language by using LLM. 
Author-email: Ephrem Yuan <areopagusworkshop@gmail.com>
License: Apache-2.0
Requires-Python: >=3.10
Requires-Dist: dspy>=2.6.6
Requires-Dist: fasttext>=0.9.3
Requires-Dist: google-auth>=2.38.0
Requires-Dist: google-genai>=1.3.0
Requires-Dist: gradio>=5.18.0
Requires-Dist: langdetect>=1.0.9
Requires-Dist: marker-pdf>=1.10.1
Requires-Dist: moviepy>=2.1.2
Requires-Dist: natsort>=8.4.0
Requires-Dist: openai-whisper>=20240930
Requires-Dist: pandas>=2.2.3
Requires-Dist: pip>=25.0.1
Requires-Dist: pyannote-audio>=3.3.2
Requires-Dist: pydub>=0.25.1
Requires-Dist: python-docx>=1.1.2
Requires-Dist: python-pptx>=1.0.2
Requires-Dist: redlines>=0.5.2
Requires-Dist: reportlab>=4.4.2
Requires-Dist: spacy>=3.8.4
Requires-Dist: weasyprint>=68.0
Requires-Dist: yt-dlp>=2025.2.19
